pyIntersecT/IntersecT.py
pyIntersecT/Logo-IntersecT.png
pyIntersecT/__init__.py
pyintersect-0.0.2.dist-info/METADATA
pyintersect-0.0.2.dist-info/WHEEL
pyintersect-0.0.2.dist-info/licenses/LICENSE
pyintersect-0.0.2.dist-info/RECORD
