Metadata-Version: 2.4
Name: pyIntersecT
Version: 0.0.2
Summary: Quantitative isopleth thermobarometry from PerpleX
Project-URL: Homepage, https://github.com/neoscalc/IntersecT
Project-URL: Bug Tracker, https://github.com/neoscalc/IntersecT/issues
Author-email: Sara Nerone <sara.nerone@unito.it>
License:                     GNU GENERAL PUBLIC LICENSE
License-File: LICENSE
Classifier: Operating System :: OS Independent
Classifier: Programming Language :: Python :: 3.10
Requires-Dist: matplotlib
Requires-Dist: numpy
Requires-Dist: pandas
Requires-Dist: pytk
